[
    {
        "nombre": "Pedro Aguero",
        "contrasenia": "Paguero",
        "edad": 23,
        "telefono": 223567121,
        "especialidad": "CARDIOLOGIA",
        "id": 1,
        "dni": "39.567.212"
    },
    {
        "nombre": "Lisandro Lopez",
        "contrasenia": "Llopez",
        "edad": 38,
        "telefono": 223671121,
        "especialidad": "PEDIATRIA",
        "id": 2,
        "dni": "35.235.712"
    },
    {
        "nombre": "Martina Sanchez",
        "contrasenia": "Msanchez",
        "edad": 28,
        "telefono": 223671212,
        "especialidad": "CLINICA",
        "id": 3,
        "dni": "40.299.981"
    },
    {
        "nombre": "Martin Dominguez",
        "contrasenia": "Mdominguez",
        "edad": 27,
        "telefono": 2236983121,
        "especialidad": "NEUROLOGIA",
        "id": 4,
        "dni": "41.577.721"
    },
    {
        "nombre": "Laura Hernandez",
        "contrasenia": "Lhernandez",
        "edad": 34,
        "telefono": 2235789312,
        "especialidad": "CARDIOLOGIA",
        "id": 5,
        "dni": "38.231.666"
    },
    {
        "nombre": "Estefania Gutierrez",
        "contrasenia": "Egutierrez",
        "edad": 51,
        "telefono": 2235781231,
        "especialidad": "PEDIATRIA",
        "id": 6,
        "dni": "32.555.121"
    },
    {
        "nombre": "Mateo Pereira",
        "contrasenia": "Mpereira",
        "edad": 50,
        "telefono": 2235982341,
        "especialidad": "CLINICA",
        "id": 7,
        "dni": "28.566.129"
    },
    {
        "nombre": "Hernan de la Fuente",
        "contrasenia": "Hfuente",
        "edad": 61,
        "telefono": 2234893111,
        "especialidad": "NEUROLOGIA",
        "id": 8,
        "dni": "19.561.222"
    },
    {
        "nombre": "Candela Alvarez",
        "contrasenia": "Calvarez",
        "edad": 28,
        "telefono": 2238955213,
        "dni": "40.561.999"
    },
    {
        "nombre": "Jorge Campos",
        "contrasenia": "Jcampos",
        "edad": 58,
        "telefono": 2236839134,
        "dni": "22.356.188"
    },
    {
        "nombre": "Miranda Sanchez",
        "contrasenia": "Msanchez",
        "edad": 41,
        "telefono": 2236819341,
        "dni": "33.561.992"
    }
]